ss_ord/__init__.py
ss_ord/ss_ord.py
ss_ord-1.0.0.post2.dist-info/METADATA
ss_ord-1.0.0.post2.dist-info/WHEEL
ss_ord-1.0.0.post2.dist-info/RECORD
