Metadata-Version: 2.4
Name: ss_ord
Version: 1.0.0.post2
Summary: String coding algorythm.
Author-email: Dimon-Dimonych-7654 <dimondimonych1@proton.me>
